README.md
setup.py
bread/__init__.py
bread/array.py
bread/boolean.py
bread/constants.py
bread/enum.py
bread/errors.py
bread/field.py
bread/integer.py
bread/lifecycle.py
bread/padding.py
bread/string.py
bread/struct.py
bread/utils.py
bread.egg-info/PKG-INFO
bread.egg-info/SOURCES.txt
bread.egg-info/dependency_links.txt
bread.egg-info/requires.txt
bread.egg-info/top_level.txt
bread/vendor/__init__.py
bread/vendor/six.py