Metadata-Version: 1.1
Name: bread
Version: 3.0.1
Summary: Binary format parsing made easier
Home-page: https://github.com/alexras/bread
Author: Alex Rasmussen
Author-email: alexras@acm.org
License: MIT
Platform: UNKNOWN
Classifier: Development Status :: 4 - Beta
Classifier: Environment :: Other Environment
Classifier: Intended Audience :: Developers
Classifier: License :: OSI Approved :: MIT License
Classifier: Natural Language :: English
Classifier: Operating System :: OS Independent
Classifier: Programming Language :: Python
Classifier: Programming Language :: Python :: 2.7
Classifier: Programming Language :: Python :: 3
Classifier: Topic :: Software Development :: Libraries :: Python Modules
Requires: bitstring
